django_darthmail/__init__.py
django_darthmail/apps.py
django_darthmail/backends.py
django_darthmail/client.py
django_darthmail/message.py
django_darthmail/serializers.py
django_darthmail/management/__init__.py
django_darthmail/management/commands/__init__.py
django_darthmail/management/commands/sendtestdarthmail.py
django_darthmail/migrations/__init__.py
django_darthmail-0.4.1.dist-info/LICENSE
django_darthmail-0.4.1.dist-info/METADATA
django_darthmail-0.4.1.dist-info/WHEEL
django_darthmail-0.4.1.dist-info/top_level.txt
django_darthmail-0.4.1.dist-info/RECORD
