Metadata-Version: 2.1
Name: django-darthmail
Version: 0.4.1
Summary: Client for the DarthMail project
Home-page: https://github.com/regiohelden/django-darthmail
Author: RegioHelden GmbH
Author-email: entwicklung@regiohelden.de
License: BSD-3-Clause
Classifier: Development Status :: 4 - Beta
Classifier: Framework :: Django
Classifier: Framework :: Django :: 2.2
Classifier: Intended Audience :: Developers
Classifier: License :: OSI Approved :: BSD License
Classifier: Natural Language :: English
Classifier: Programming Language :: Python :: 3
Classifier: Programming Language :: Python :: 3.6
Classifier: Programming Language :: Python :: 3.7
Classifier: Programming Language :: Python :: 3.8
Classifier: Topic :: Communications :: Email
License-File: LICENSE
Requires-Dist: django >=4.2
Requires-Dist: requests >=2.31.0
Requires-Dist: pillow >=10.0.0
